ebs/__init__.py
ebs/linuxnode/__init__.py
ebs/linuxnode/netconfig/__init__.py
ebs/linuxnode/netconfig/config.py
ebs/linuxnode/netconfig/core.py
ebs/linuxnode/netconfig/server.py
ebs/linuxnode/netconfig/wifi.py
ebs/linuxnode/netconfig/app/asset-manifest.json
ebs/linuxnode/netconfig/app/favicon.ico
ebs/linuxnode/netconfig/app/index.html
ebs/linuxnode/netconfig/app/logo192.png
ebs/linuxnode/netconfig/app/logo512.png
ebs/linuxnode/netconfig/app/manifest.json
ebs/linuxnode/netconfig/app/robots.txt
ebs/linuxnode/netconfig/app/static/css/2.8c49bb0a.chunk.css
ebs/linuxnode/netconfig/app/static/css/2.8c49bb0a.chunk.css.map
ebs/linuxnode/netconfig/app/static/css/main.ad78b6b4.chunk.css
ebs/linuxnode/netconfig/app/static/css/main.ad78b6b4.chunk.css.map
ebs/linuxnode/netconfig/app/static/js/2.9c412b52.chunk.js
ebs/linuxnode/netconfig/app/static/js/2.9c412b52.chunk.js.LICENSE.txt
ebs/linuxnode/netconfig/app/static/js/2.9c412b52.chunk.js.map
ebs/linuxnode/netconfig/app/static/js/main.7215c13f.chunk.js
ebs/linuxnode/netconfig/app/static/js/main.7215c13f.chunk.js.map
ebs/linuxnode/netconfig/app/static/js/runtime-main.f3d7ae9b.js
ebs/linuxnode/netconfig/app/static/js/runtime-main.f3d7ae9b.js.map
ebs/linuxnode/netconfig/app/static/media/logo.daee85b9.png
ebs/linuxnode/netconfig/app/static/media/roboto-all-400-normal.376ea5d9.woff
ebs/linuxnode/netconfig/app/static/media/roboto-cyrillic-400-normal.5e493812.woff2
ebs/linuxnode/netconfig/app/static/media/roboto-cyrillic-ext-400-normal.493afe7a.woff2
ebs/linuxnode/netconfig/app/static/media/roboto-greek-400-normal.1cbfc636.woff2
ebs/linuxnode/netconfig/app/static/media/roboto-greek-ext-400-normal.e769aa77.woff2
ebs/linuxnode/netconfig/app/static/media/roboto-latin-400-normal.4673b453.woff2
ebs/linuxnode/netconfig/app/static/media/roboto-latin-ext-400-normal.c3dcdbd5.woff2
ebs/linuxnode/netconfig/app/static/media/roboto-vietnamese-400-normal.c0bec65d.woff2
ebs/linuxnode/netconfig/default/config.ini
ebs_linuxnode_netconfig-0.1.6.dist-info/METADATA
ebs_linuxnode_netconfig-0.1.6.dist-info/WHEEL
ebs_linuxnode_netconfig-0.1.6.dist-info/entry_points.txt
ebs_linuxnode_netconfig-0.1.6.dist-info/top_level.txt
ebs_linuxnode_netconfig-0.1.6.dist-info/RECORD
