Metadata-Version: 2.1
Name: ebs-linuxnode-netconfig
Version: 0.1.6
Summary: Network configuration infrastructure for embedded linux nodes
Home-page: UNKNOWN
Author: Chintalagiri Shashank
Author-email: shashank.chintalagiri@gmail.com
License: UNKNOWN
Platform: UNKNOWN
Classifier: Development Status :: 5 - Production/Stable
Classifier: Intended Audience :: Developers
Classifier: License :: OSI Approved :: GNU General Public License v3 or later (GPLv3+)
Classifier: Programming Language :: Python
Classifier: Programming Language :: Python :: 3
Classifier: Programming Language :: Python :: 3.6
Classifier: Operating System :: POSIX :: Linux
Requires-Dist: six
Requires-Dist: appdirs
Requires-Dist: setuptools-scm
Requires-Dist: fastapi
Requires-Dist: python-multipart
Requires-Dist: python-jose[cryptography]
Requires-Dist: passlib[bcrypt]
Requires-Dist: aiofiles
Requires-Dist: uvicorn
Requires-Dist: loguru
Requires-Dist: wpasupplicantconf
